{
  "title": "Programa de cultos y actos",
  "subtitle": "",
  "tagline": "Santa Águeda y Santa Apolonia 2024",
  "days": [
    {
      "title": "",
      "event": [
        {
          "title": "SANTA MISA EN HONOR A SANTA ÁGUEDA Y SANTA APOLONIA",
          "time": "13.00 H.",
          "description": "A las 13.00 H. tendrá lugar la Santa Misa en Honor a Santa Águeda y Santa Apolonia. En la misma se bendecirán las tortas.\n\nAquellas personas que lo deseen, podrán adquirir tortas a un precio de 0,50 € a la finalización de la eucaristía.\n",
          "location": "Iglesia de San Francisco",
          "map": "https://www.google.com/maps/place/Iglesia+y+convento+de+San+Francisco/@39.3887879,-3.207922,17z/data=!4m14!1m7!3m6!1s0xd69aeefb3165823:0x169fe142d9dfcbbe!2sIglesia+y+convento+de+San+Francisco!8m2!3d39.3887879!4d-3.2053471!16s%2Fg%2F11bxg1p81f!3m5!1s0xd69aeefb3165823:0x169fe142d9dfcbbe!8m2!3d39.3887879!4d-3.2053471!16s%2Fg%2F11bxg1p81f?entry=ttu"
        }
      ]
    }
  ]
}